{
    "id": "file://C:/Users/thsch/IdeaProjects/fsklab-json/1.0.4/vocabularies/population.json",
    "definitions": {
        "population": {
            "type": "string",
            "enum": [
                "human consumer, seniors",
                "infant food",
                "human consumer, no age specification",
                "infant food, 3 - 6 months",
                "human consumer, weight-reducers",
                "human consumer, pregnant or lactanting women",
                "human consumer, adult",
                "infant food, 6 - 12 months",
                "human consumer, men",
                "infant food, 0 - 6 months",
                "human consumer, teenagers",
                "human consumer, four years and above",
                "human consumer, athletes",
                "human consumer, women",
                "infant food, 0 - 3 months",
                "toddler food, from 12 months onwards",
                "human consumer, menopaused women",
                "infant or toddler food",
                "human consumer, bodybuilders",
                "children less than four years"
            ]
        },
        "foodon": {
            "type": "string",
            "enum": [
                "03510253",
                "03510020",
                "03510024",
                "03510251",
                "03510261",
                "03510256",
                "3510250",
                "3510191",
                "03510262",
                "3510189",
                "3510266",
                "3510188",
                "3510190",
                "03510254",
                "03510260",
                "03510259",
                "3510192",
                "3510263",
                "03510255",
                "03510252"
            ]
        }
    }
}